<?xml version="1.0" encoding="UTF-8"?>
<conversation id="CHT_ARZ_20130312.0003" medium="IM" donated="true">
  <su id="s0">
    <messages>
      <message id="m0000" medium="IM" time="2013-03-12 21:40:15 UTC" participant="138112">Mostafa</message>
    </messages>
    <body type="original">Mostafa</body><body type="transliterated">مصطفي</body>
  </su>
  <su id="s1">
    <messages>
      <message id="m0001" medium="IM" time="2013-03-12 21:40:20 UTC" participant="138112">Leh sortak black</message>
    </messages>
    <body type="original">Leh sortak black</body><body type="transliterated">ليه صورتك بلاشك</body>
  </su>
  <su id="s2">
    <messages>
      <message id="m0002" medium="IM" time="2013-03-12 21:43:10 UTC" participant="138329">3ady mafsh haga</message>
    </messages>
    <body type="original">3ady mafsh haga</body><body type="transliterated">عادي مفش حاجه</body>
  </su>
  <su id="s3">
    <messages>
      <message id="m0003" medium="IM" time="2013-03-12 21:44:37 UTC" participant="138112">Mashy</message>
    </messages>
    <body type="original">Mashy</body><body type="transliterated">ماشي</body>
  </su>
  <su id="s4">
    <messages>
      <message id="m0006" medium="IM" time="2013-03-12 22:01:22 UTC" participant="138112">:D</message>
    </messages>
    <body type="original">:D</body><body type="transliterated">: يد</body>
  </su>
  <su id="s5">
    <messages>
      <message id="m0008" medium="IM" time="2013-03-12 22:01:52 UTC" participant="138329">Haahaa</message>
    </messages>
    <body type="original">Haahaa</body><body type="transliterated">هاها</body>
  </su>
  <su id="s6">
    <messages>
      <message id="m0009" medium="IM" time="2013-03-12 22:01:54 UTC" participant="138329">Allaahhaa</message>
    </messages>
    <body type="original">Allaahhaa</body><body type="transliterated">الاها</body>
  </su>
  <su id="s7">
    <messages>
      <message id="m0010" medium="IM" time="2013-03-12 22:24:21 UTC" participant="138329">Messiiiiiiiiiiii</message>
    </messages>
    <body type="original">Messiiiiiiiiiiii</body><body type="transliterated">ميسي</body>
  </su>
  <su id="s8">
    <messages>
      <message id="m0011" medium="IM" time="2013-03-12 22:24:24 UTC" participant="138329">Alllahahajahahahaha</message>
    </messages>
    <body type="original">Alllahahajahahahaha</body><body type="transliterated">allahahajahahahaha</body>
  </su>
  <su id="s9">
    <messages>
      <message id="m0012" medium="IM" time="2013-03-12 22:24:45 UTC" participant="138112">Hahahaha</message>
    </messages>
    <body type="original">Hahahaha</body><body type="transliterated">hahahaha</body>
  </su>
  <su id="s10">
    <messages>
      <message id="m0013" medium="IM" time="2013-03-12 22:24:47 UTC" participant="138112">:D</message>
    </messages>
    <body type="original">:D</body><body type="transliterated">: يد</body>
  </su>
  <su id="s11">
    <messages>
      <message id="m0014" medium="IM" time="2013-03-12 22:25:01 UTC" participant="138329">Hahaha</message>
    </messages>
    <body type="original">Hahaha</body><body type="transliterated">هاهاها</body>
  </su>
  <su id="s12">
    <messages>
      <message id="m0015" medium="IM" time="2013-03-12 22:59:12 UTC" participant="138329">Kfaya kda</message>
    </messages>
    <body type="original">Kfaya kda</body><body type="transliterated">كفايه كده</body>
  </su>
  <su id="s13">
    <messages>
      <message id="m0016" medium="IM" time="2013-03-12 22:59:18 UTC" participant="138329">Dool bynt2mo</message>
    </messages>
    <body type="original">Dool bynt2mo</body><body type="transliterated">دول بينتقم</body>
  </su>
  <su id="s14">
    <messages>
      <message id="m0017" medium="IM" time="2013-03-12 23:08:50 UTC" participant="138112">Hahahaha 3-0 lesa?</message>
    </messages>
    <body type="original">Hahahaha 3-0 lesa?</body><body type="transliterated">hahahaha 3 - 0 لسه ?</body>
  </su>
  <su id="s15">
    <messages>
      <message id="m0018" medium="IM" time="2013-03-12 23:08:54 UTC" participant="138112">Afalt el game</message>
    </messages>
    <body type="original">Afalt el game</body><body type="transliterated">قفلت ال جم</body>
  </su>
  <su id="s16">
    <messages>
      <message id="m0019" medium="IM" time="2013-03-12 23:13:49 UTC" participant="138329">Ahhh</message>
    </messages>
    <body type="original">Ahhh</body><body type="transliterated">اه</body>
  </su>
  <su id="s17">
    <messages>
      <message id="m0020" medium="IM" time="2013-03-12 23:24:59 UTC" participant="138112">Ehda hahahaha</message>
    </messages>
    <body type="original">Ehda hahahaha</body><body type="transliterated">اهدا hahahaha</body>
  </su>
  <su id="s18">
    <messages>
      <message id="m0022" medium="IM" time="2013-03-12 23:33:01 UTC" participant="138329">Hahahahahahhahh</message>
    </messages>
    <body type="original">Hahahahahahhahh</body><body type="transliterated">hahahahahahhahh</body>
  </su>
  <su id="s19">
    <messages>
      <message id="m0023" medium="IM" time="2013-03-12 23:33:15 UTC" participant="138112">Shoft!!! HAHAHAHAHAHAHA</message>
    </messages>
    <body type="original">Shoft!!! HAHAHAHAHAHAHA</body><body type="transliterated">شفت ! ! ! hahahahahahaha</body>
  </su>
  <su id="s20">
    <messages>
      <message id="m0024" medium="IM" time="2013-03-12 23:33:27 UTC" participant="138329">Whooooo</message>
    </messages>
    <body type="original">Whooooo</body><body type="transliterated">وهو</body>
  </su>
  <su id="s21">
    <messages>
      <message id="m0025" medium="IM" time="2013-03-12 23:33:41 UTC" participant="138112">Beyente2mo hahaha</message>
    </messages>
    <body type="original">Beyente2mo hahaha</body><body type="transliterated">بينتقم هاهاها</body>
  </su>
  <su id="s22">
    <messages>
      <message id="m0026" medium="IM" time="2013-03-12 23:33:54 UTC" participant="138329">Ahhh wallahi</message>
    </messages>
    <body type="original">Ahhh wallahi</body><body type="transliterated">اه والله</body>
  </su>
  <su id="s23">
    <messages>
      <message id="m0027" medium="IM" time="2013-03-12 23:34:34 UTC" participant="138329">El7777</message>
    </messages>
    <body type="original">El7777</body><body type="transliterated">الح</body>
  </su>
  <su id="s24">
    <messages>
      <message id="m0029" medium="IM" time="2013-03-12 23:42:14 UTC" participant="138329">Haahahahahaaa</message>
    </messages>
    <body type="original">Haahahahahaaa</body><body type="transliterated">haahahahahaa</body>
  </su>
  <su id="s25">
    <messages>
      <message id="m0030" medium="IM" time="2013-03-12 23:42:16 UTC" participant="138329">Eh da</message>
    </messages>
    <body type="original">Eh da</body><body type="transliterated">ايه ده</body>
  </su>
  <su id="s26">
    <messages>
      <message id="m0031" medium="IM" time="2013-03-12 23:42:29 UTC" participant="138112">Hahahahaha</message>
    </messages>
    <body type="original">Hahahahaha</body><body type="transliterated">hahahahaha</body>
  </su>
  <su id="s27">
    <messages>
      <message id="m0032" medium="IM" time="2013-03-12 23:42:41 UTC" participant="138329">Ahhahahaa</message>
    </messages>
    <body type="original">Ahhahahaa</body><body type="transliterated">ahhahahaa</body>
  </su>
  <su id="s28">
    <messages>
      <message id="m0033" medium="IM" time="2013-03-12 23:42:48 UTC" participant="138329">3amla eih</message>
    </messages>
    <body type="original">3amla eih</body><body type="transliterated">عامله ايه</body>
  </su>
  <su id="s29">
    <messages>
      <message id="m0034" medium="IM" time="2013-03-12 23:43:00 UTC" participant="138112">Kwayesa :D</message>
    </messages>
    <body type="original">Kwayesa :D</body><body type="transliterated">كويسه : يد</body>
  </su>
  <su id="s30">
    <messages>
      <message id="m0035" medium="IM" time="2013-03-12 23:43:01 UTC" participant="138112">W enta</message>
    </messages>
    <body type="original">W enta</body><body type="transliterated">و انت</body>
  </su>
  <su id="s31">
    <messages>
      <message id="m0036" medium="IM" time="2013-03-12 23:43:13 UTC" participant="138329">Kwayes</message>
    </messages>
    <body type="original">Kwayes</body><body type="transliterated">كويس</body>
  </su>
  <su id="s32">
    <messages>
      <message id="m0037" medium="IM" time="2013-03-12 23:43:19 UTC" participant="138329">El7 akheran</message>
    </messages>
    <body type="original">El7 akheran</body><body type="transliterated">الح اخيرا</body>
  </su>
  <su id="s33">
    <messages>
      <message id="m0038" medium="IM" time="2013-03-12 23:45:06 UTC" participant="138112">Far7an? Hahaha</message>
    </messages>
    <body type="original">Far7an? Hahaha</body><body type="transliterated">فرحان ? هاهاها</body>
  </su>
  <su id="s34">
    <messages>
      <message id="m0039" medium="IM" time="2013-03-12 23:45:29 UTC" participant="138329">Fash5</message>
    </messages>
    <body type="original">Fash5</body><body type="transliterated">فشخ</body>
  </su>
  <su id="s35">
    <messages>
      <message id="m0040" medium="IM" time="2013-03-12 23:45:52 UTC" participant="138329">Ba2lhom talatt match-at by5saroo</message>
    </messages>
    <body type="original">Ba2lhom talatt match-at by5saroo</body><body type="transliterated">بقلهم تالت ماتش - اه بيخسرو</body>
  </su>
  <su id="s36">
    <messages>
      <message id="m0041" medium="IM" time="2013-03-12 23:45:55 UTC" participant="138112">Hahahaha :*</message>
    </messages>
    <body type="original">Hahahaha :*</body><body type="transliterated">hahahaha : ذ</body>
  </su>
  <su id="s37">
    <messages>
      <message id="m0042" medium="IM" time="2013-03-12 23:45:59 UTC" participant="138112">Ahh</message>
    </messages>
    <body type="original">Ahh</body><body type="transliterated">اه</body>
  </su>
  <su id="s38">
    <messages>
      <message id="m0043" medium="IM" time="2013-03-12 23:46:16 UTC" participant="138329">:*</message>
    </messages>
    <body type="original">:*</body><body type="transliterated">: ذ</body>
  </su>
  <su id="s39">
    <messages>
      <message id="m0044" medium="IM" time="2013-03-12 23:46:35 UTC" participant="138329">Akhabarek fel beet eh haterg3lna emta</message>
    </messages>
    <body type="original">Akhabarek fel beet eh haterg3lna emta</body><body type="transliterated">اخبارك فل بيه ايه هترجعلنا امته</body>
  </su>
  <su id="s40">
    <messages>
      <message id="m0045" medium="IM" time="2013-03-12 23:46:41 UTC" participant="138329">Wa7hteni :p</message>
    </messages>
    <body type="original">Wa7hteni :p</body><body type="transliterated">wa7hteni : ف</body>
  </su>
  <su id="s41">
    <messages>
      <message id="m0046" medium="IM" time="2013-03-12 23:46:52 UTC" participant="138112">Bakol w banam :D</message>
    </messages>
    <body type="original">Bakol w banam :D</body><body type="transliterated">بكل و بنام : يد</body>
  </su>
  <su id="s42">
    <messages>
      <message id="m0047" medium="IM" time="2013-03-12 23:46:57 UTC" participant="138112">Enta kaman hahahaha</message>
    </messages>
    <body type="original">Enta kaman hahahaha</body><body type="transliterated">انت كمان hahahaha</body>
  </su>
  <su id="s43">
    <messages>
      <message id="m0048" medium="IM" time="2013-03-12 23:47:13 UTC" participant="138329">Haahaaha</message>
    </messages>
    <body type="original">Haahaaha</body><body type="transliterated">هاهاها</body>
  </su>
  <su id="s44">
    <messages>
      <message id="m0049" medium="IM" time="2013-03-12 23:47:18 UTC" participant="138329">:D</message>
    </messages>
    <body type="original">:D</body><body type="transliterated">: يد</body>
  </su>
  <su id="s45">
    <messages>
      <message id="m0050" medium="IM" time="2013-03-13 15:54:45 UTC" participant="138329">Joe</message>
    </messages>
    <body type="original">Joe</body><body type="transliterated">جوه</body>
  </su>
  <su id="s46">
    <messages>
      <message id="m0051" medium="IM" time="2013-03-14 01:19:15 UTC" participant="138329">Mabtrodesh 3alia ha!!</message>
    </messages>
    <body type="original">Mabtrodesh 3alia ha!!</body><body type="transliterated">mabtrodesh عليه هه ! !</body>
  </su>
  <su id="s47">
    <messages>
      <message id="m0052" medium="IM" time="2013-03-14 01:26:33 UTC" participant="138112">Enta maba3tsh haga</message>
    </messages>
    <body type="original">Enta maba3tsh haga</body><body type="transliterated">انت مبعتش حاجه</body>
  </su>
  <su id="s48">
    <messages>
      <message id="m0053" medium="IM" time="2013-03-14 06:25:09 UTC" participant="138329">Ahh tyb</message>
    </messages>
    <body type="original">Ahh tyb</body><body type="transliterated">اه طيب</body>
  </su>
</conversation>
