<?xml version="1.0" encoding="utf-8"?>
<conversation id="CHT_ARZ_20130829.0011" medium="CHT" donated="true">
  <su id="s0">
    <source>والله وحشتيني وقلت امسي عليكي حاسة اني بقالي كتير ماشفتكيش</source>
    <annotated_arabizi>
      <token id="t0">والله</token>
      <token id="t1">وحشتيني</token>
      <token id="t2">وقلت</token>
      <token id="t3">امسي</token>
      <token id="t4">عليكي</token>
      <token id="t5">حاسة</token>
      <token id="t6">اني</token>
      <token id="t7">بقالي</token>
      <token id="t8">كتير</token>
      <token id="t9">ماشفتكيش</token>
    </annotated_arabizi>
    <auto_transliteration>والله وحشتيني وقلت امسي عليكي HAsp أني بقا[-]لي كثير ماشفتكيش</auto_transliteration>
    <corrected_transliteration>والله وحشتيني وقلت امسي عليكي HAsp أني بقا[-]لي كثير ماشفتكيش</corrected_transliteration>
    <retokenized_transliteration>والله وحشتيني وقلت امسي عليكي HAsp أني بقا لي كثير ماشفتكيش</retokenized_transliteration>
    <messages>
      <message id="m0001" time="2013-08-29 21:05:00 UTC" participant="139230">والله وحشتيني وقلت امسي عليكي</message>
      <message id="m0002" time="2013-08-29 21:05:00 UTC" participant="139230">حاسة اني بقالي كتير ماشفتكيش</message>
    </messages>
  </su>
  <su id="s1">
    <source>Wallahy wa7shany awy wana kaman</source>
    <annotated_arabizi>
      <token id="t0">Wallahy</token>
      <token id="t1">wa7shany</token>
      <token id="t2">awy</token>
      <token id="t3">wana</token>
      <token id="t4">kaman</token>
    </annotated_arabizi>
    <auto_transliteration>والله واحشني قوي وانا كمان</auto_transliteration>
    <corrected_transliteration>والله واحشني قوي وانا كمان</corrected_transliteration>
    <retokenized_transliteration>والله واحشني قوي وانا كمان</retokenized_transliteration>
    <messages>
      <message id="m0003" time="2013-08-29 21:14:00 UTC" participant="139880">Wallahy wa7shany awy</message>
      <message id="m0004" time="2013-08-29 21:14:00 UTC" participant="139880">wana kaman</message>
    </messages>
  </su>
  <su id="s2">
    <source>Bas msada3a w damy t2eel awyyyyy</source>
    <annotated_arabizi>
      <token id="t0">Bas</token>
      <token id="t1">msada3a</token>
      <token id="t2">w</token>
      <token id="t3">damy</token>
      <token id="t4">t2eel</token>
      <token id="t5">awyy</token>
    </annotated_arabizi>
    <auto_transliteration>بس مصدعة و[+] دمي تقيل قوي</auto_transliteration>
    <corrected_transliteration>بس مصدعة و[+] دمي تقيل قوي</corrected_transliteration>
    <retokenized_transliteration>بس مصدعة ودمي تقيل قوي</retokenized_transliteration>
    <messages>
      <message id="m0005" time="2013-08-29 21:15:00 UTC" participant="139880">Bas msada3a w damy t2eel awyyyyy</message>
    </messages>
  </su>
  <su id="s3">
    <source>Ana kont nawya akalemek bokra 7ayso el suspense</source>
    <annotated_arabizi>
      <token id="t0">Ana</token>
      <token id="t1">kont</token>
      <token id="t2">nawya</token>
      <token id="t3">akalemek</token>
      <token id="t4">bokra</token>
      <token id="t5">7ayso</token>
      <token id="t6">el</token>
      <token id="t7" tag="foreign">suspense</token>
    </annotated_arabizi>
    <auto_transliteration>انا كنت ناوية اكلمك بكرة حيسة ال[+] سسبنز</auto_transliteration>
    <corrected_transliteration>انا كنت ناوية أاكلمك بكرة حيت ال[+] سسبنز</corrected_transliteration>
    <retokenized_transliteration>انا كنت ناوية أاكلمك بكرة حيت السسبنز</retokenized_transliteration>
    <messages>
      <message id="m0005" time="2013-08-29 21:15:00 UTC" participant="139880">Bas msada3a w damy t2eel awyyyyy</message>
      <message id="m0006" time="2013-08-29 21:15:00 UTC" participant="139880">Ana kont nawya akalemek bokra</message>
      <message id="m0007" time="2013-08-29 21:16:00 UTC" participant="139880">7ayso el suspense</message>
    </messages>
  </su>
  <su id="s4">
    <source>انتي كمان وحشاني قوي وتقريبا بقالنا 3اسابيع ماشفناش بعض ايوا اما نشوف بكره دول ناويين على ايه</source>
    <annotated_arabizi>
      <token id="t0">انتي</token>
      <token id="t1">كمان</token>
      <token id="t2">وحشاني</token>
      <token id="t3">قوي</token>
      <token id="t4">وتقريبا</token>
      <token id="t5">بقالنا</token>
      <token id="t6">3اسابيع</token>
      <token id="t7">ماشفناش</token>
      <token id="t8">بعض</token>
      <token id="t9">ايوا</token>
      <token id="t10">اما</token>
      <token id="t11">نشوف</token>
      <token id="t12">بكره</token>
      <token id="t13">دول</token>
      <token id="t14">ناويين</token>
      <token id="t15">على</token>
      <token id="t16">ايه</token>
    </annotated_arabizi>
    <auto_transliteration>انتي كمان وحشاني qwy وتقريبا بقا[-]لنا 3اسابيع ماشفناش bED ايوا أما نشوف بكرة دول ناويين على أيه</auto_transliteration>
    <corrected_transliteration>انتي كمان وحشاني qwy وتقريبا بقا[-]لنا 3اسابيع ماشفناش bED ايوا أما نشوف بكرة دول ناويين على أيه</corrected_transliteration>
    <retokenized_transliteration>انتي كمان وحشاني qwy وتقريبا بقا لنا 3اسابيع ماشفناش bED ايوا أما نشوف بكرة دول ناويين على أيه</retokenized_transliteration>
    <messages>
      <message id="m0008" time="2013-08-29 21:34:00 UTC" participant="139230">انتي كمان وحشاني قوي وتقريبا بقالنا 3اسابيع ماشفناش بعض</message>
      <message id="m0009" time="2013-08-29 21:35:00 UTC" participant="139230">ايوا اما نشوف بكره دول ناويين على ايه</message>
    </messages>
  </su>
  <su id="s5">
    <source>سلامتك الف سلامة لازم الصداع دا يكون له خل</source>
    <annotated_arabizi>
      <token id="t0">سلامتك</token>
      <token id="t1">الف</token>
      <token id="t2">سلامة</token>
      <token id="t3">لازم</token>
      <token id="t4">الصداع</token>
      <token id="t5">دا</token>
      <token id="t6">يكون</token>
      <token id="t7">له</token>
      <token id="t8">خل</token>
    </annotated_arabizi>
    <auto_transliteration>سلامتك الف سلامة لازم الصداع dA ykwn lh خل</auto_transliteration>
    <corrected_transliteration>سلامتك الف سلامة لازم الصداع dA ykwn lh خل</corrected_transliteration>
    <retokenized_transliteration>سلامتك الف سلامة لازم الصداع dA ykwn lh خل</retokenized_transliteration>
    <messages>
      <message id="m0010" time="2013-08-29 21:35:00 UTC" participant="139230">سلامتك الف سلامة</message>
      <message id="m0011" time="2013-08-29 21:35:00 UTC" participant="139230">لازم الصداع دا يكون له خل</message>
    </messages>
  </su>
  <su id="s6">
    <source>قصدى حل</source>
    <annotated_arabizi>
      <token id="t0">قصدى</token>
      <token id="t1">حل</token>
    </annotated_arabizi>
    <auto_transliteration>قصدي حل</auto_transliteration>
    <corrected_transliteration>قصدي حل</corrected_transliteration>
    <retokenized_transliteration>قصدي حل</retokenized_transliteration>
    <messages>
      <message id="m0012" time="2013-08-29 21:38:00 UTC" participant="139230">قصدى حل </message>
    </messages>
  </su>
  <su id="s7">
    <source>yenfa3 khal bardo saba7 el kheir</source>
    <annotated_arabizi>
      <token id="t0">yenfa3</token>
      <token id="t1">khal</token>
      <token id="t2">bardo</token>
      <token id="t3">saba7</token>
      <token id="t4">el</token>
      <token id="t5">kheir</token>
    </annotated_arabizi>
    <auto_transliteration>ينفع خل برضه صباح ال[+] خير</auto_transliteration>
    <corrected_transliteration>ينفع خل برضه صباح ال[+] خير</corrected_transliteration>
    <retokenized_transliteration>ينفع خل برضه صباح الخير</retokenized_transliteration>
    <messages>
      <message id="m0013" time="2013-08-29 21:45:00 UTC" participant="139880">yenfa3 khal bardo</message>
      <message id="m0014" time="2013-08-30 06:44:00 UTC" participant="139880">saba7 el kheir</message>
    </messages>
  </su>
  <su id="s8">
    <source>ايه اللي مصحيكي ولا خلاص بطلتي تنامي</source>
    <annotated_arabizi>
      <token id="t0">ايه</token>
      <token id="t1">اللي</token>
      <token id="t2">مصحيكي</token>
      <token id="t3">ولا</token>
      <token id="t4">خلاص</token>
      <token id="t5">بطلتي</token>
      <token id="t6">تنامي</token>
    </annotated_arabizi>
    <auto_transliteration>أيه اللي مصحيكي ولا خلاص بطلتي تنامي</auto_transliteration>
    <corrected_transliteration>أيه اللي مصحيكي ولا خلاص بطلتي تنامي</corrected_transliteration>
    <retokenized_transliteration>أيه اللي مصحيكي ولا خلاص بطلتي تنامي</retokenized_transliteration>
    <messages>
      <message id="m0015" time="2013-08-30 06:44:00 UTC" participant="139880">ايه اللي مصحيكي</message>
      <message id="m0016" time="2013-08-30 06:44:00 UTC" participant="139880">ولا خلاص بطلتي تنامي</message>
    </messages>
  </su>
  <su id="s9">
    <source>والله عندي ارق فظيع انا كمان اخدت منوم بس بس مفيش فايدة والله الواحد مخه ما بيرتاحش انتي كمان شكلك ما نمتيش</source>
    <annotated_arabizi>
      <token id="t0">والله</token>
      <token id="t1">عندي</token>
      <token id="t2">ارق</token>
      <token id="t3">فظيع</token>
      <token id="t4">انا</token>
      <token id="t5">كمان</token>
      <token id="t6">اخدت</token>
      <token id="t7">منوم</token>
      <token id="t8">بس</token>
      <token id="t9">بس</token>
      <token id="t10">مفيش</token>
      <token id="t11">فايدة</token>
      <token id="t12">والله</token>
      <token id="t13">الواحد</token>
      <token id="t14">مخه</token>
      <token id="t15">ما</token>
      <token id="t16">بيرتاحش</token>
      <token id="t17">انتي</token>
      <token id="t18">كمان</token>
      <token id="t19">شكلك</token>
      <token id="t20">ما</token>
      <token id="t21">نمتيش</token>
    </annotated_arabizi>
    <auto_transliteration>والله عندي ارق فظيع انا كمان Axdt mnwm bs bs مفيهش فايدة والله الواحد مخه ما بيرتاحش انتي كمان شكلك ما نمتيش</auto_transliteration>
    <corrected_transliteration>والله عندي ارق فظيع انا كمان Axdt mnwm bs bs مفيهش فايدة والله الواحد مخه ما بيرتاحش انتي كمان شكلك ما نمتيش</corrected_transliteration>
    <retokenized_transliteration>والله عندي ارق فظيع انا كمان Axdt mnwm bs bs مفيهش فايدة والله الواحد مخه ما بيرتاحش انتي كمان شكلك ما نمتيش</retokenized_transliteration>
    <messages>
      <message id="m0017" time="2013-08-30 07:06:00 UTC" participant="139230">والله عندي ارق فظيع</message>
      <message id="m0018" time="2013-08-30 07:06:00 UTC" participant="139230">انا كمان اخدت منوم بس بس مفيش فايدة</message>
      <message id="m0019" time="2013-08-30 07:07:00 UTC" participant="139230">والله الواحد مخه ما بيرتاحش</message>
      <message id="m0020" time="2013-08-30 07:07:00 UTC" participant="139230">انتي كمان شكلك ما نمتيش</message>
    </messages>
  </su>
  <su id="s10">
    <source>وانا كمان اخدت دوا للصداع بينيم</source>
    <annotated_arabizi>
      <token id="t0">وانا</token>
      <token id="t1">كمان</token>
      <token id="t2">اخدت</token>
      <token id="t3">دوا</token>
      <token id="t4">للصداع</token>
      <token id="t5">بينيم</token>
    </annotated_arabizi>
    <auto_transliteration>وانا كمان Axdt دوا للصداع بينيم</auto_transliteration>
    <corrected_transliteration>وانا كمان Axdt دوا للصداع بينيم</corrected_transliteration>
    <retokenized_transliteration>وانا كمان Axdt دوا للصداع بينيم</retokenized_transliteration>
    <messages>
      <message id="m0021" time="2013-08-30 07:07:00 UTC" participant="139880">وانا كمان</message>
      <message id="m0022" time="2013-08-30 07:08:00 UTC" participant="139880">اخدت دوا للصداع بينيم</message>
    </messages>
  </su>
  <su id="s11">
    <source>النوم بقى صعب في الظروف دي</source>
    <annotated_arabizi>
      <token id="t0">النوم</token>
      <token id="t1">بقى</token>
      <token id="t2">صعب</token>
      <token id="t3">في</token>
      <token id="t4">الظروف</token>
      <token id="t5">دي</token>
    </annotated_arabizi>
    <auto_transliteration>النوم بقى SEb fy الظروف دي</auto_transliteration>
    <corrected_transliteration>النوم بقى SEb fy الظروف دي</corrected_transliteration>
    <retokenized_transliteration>النوم بقى SEb fy الظروف دي</retokenized_transliteration>
    <messages>
      <message id="m0023" time="2013-08-30 07:08:00 UTC" participant="139230">النوم بقى صعب في الظروف دي</message>
    </messages>
  </su>
  <su id="s12">
    <source>وقاعدة زي القرد بس الشارع فاضي تماما</source>
    <annotated_arabizi>
      <token id="t0">وقاعدة</token>
      <token id="t1">زي</token>
      <token id="t2">القرد</token>
      <token id="t3">بس</token>
      <token id="t4">الشارع</token>
      <token id="t5">فاضي</token>
      <token id="t6">تماما</token>
    </annotated_arabizi>
    <auto_transliteration>وقاعدة زي القرد bs الشارع فاضي تماما</auto_transliteration>
    <corrected_transliteration>وقاعدة زي القرد bs الشارع فاضي تماما</corrected_transliteration>
    <retokenized_transliteration>وقاعدة زي القرد bs الشارع فاضي تماما</retokenized_transliteration>
    <messages>
      <message id="m0024" time="2013-08-30 07:08:00 UTC" participant="139880">وقاعدة زي القرد</message>
      <message id="m0025" time="2013-08-30 07:08:00 UTC" participant="139880">بس الشارع فاضي تماما</message>
    </messages>
  </su>
  <su id="s13">
    <source>ربنا يعدي النهاردة الى خير</source>
    <annotated_arabizi>
      <token id="t0">ربنا</token>
      <token id="t1">يعدي</token>
      <token id="t2">النهاردة</token>
      <token id="t3">الى</token>
      <token id="t4">خير</token>
    </annotated_arabizi>
    <auto_transliteration>ربنا يعدي النهارده اللي خير</auto_transliteration>
    <corrected_transliteration>ربنا يعدي النهارده اللي خير</corrected_transliteration>
    <retokenized_transliteration>ربنا يعدي النهارده اللي خير</retokenized_transliteration>
    <messages>
      <message id="m0026" time="2013-08-30 07:09:00 UTC" participant="139230">ربنا يعدي النهاردة الى خير</message>
    </messages>
  </su>
  <su id="s14">
    <source>مافيش اي حاجة ان شاء الله</source>
    <annotated_arabizi>
      <token id="t0">مافيش</token>
      <token id="t1">اي</token>
      <token id="t2">حاجة</token>
      <token id="t3">ان</token>
      <token id="t4">شاء</token>
      <token id="t5">الله</token>
    </annotated_arabizi>
    <auto_transliteration>ما[-]فيهش اي HAjp إن $A' الله</auto_transliteration>
    <corrected_transliteration>ما[-]فيهش اي HAjp إن $A' الله</corrected_transliteration>
    <retokenized_transliteration>ما فيهش اي HAjp إن $A' الله</retokenized_transliteration>
    <messages>
      <message id="m0027" time="2013-08-30 07:09:00 UTC" participant="139880">مافيش اي حاجة</message>
      <message id="m0028" time="2013-08-30 07:09:00 UTC" participant="139880">ان شاء الله</message>
    </messages>
  </su>
  <su id="s15">
    <source>فرقعه صابون</source>
    <annotated_arabizi>
      <token id="t0">فرقعه</token>
      <token id="t1">صابون</token>
    </annotated_arabizi>
    <auto_transliteration>فرقعة صابون</auto_transliteration>
    <corrected_transliteration>فرقعة صابون</corrected_transliteration>
    <retokenized_transliteration>فرقعة صابون</retokenized_transliteration>
    <messages>
      <message id="m0029" time="2013-08-30 07:09:00 UTC" participant="139880">فرقعه صابون</message>
    </messages>
  </su>
  <su id="s16">
    <source>لا انا عندي الشارع فيه حركةة على غير العادة</source>
    <annotated_arabizi>
      <token id="t0">لا</token>
      <token id="t1">انا</token>
      <token id="t2">عندي</token>
      <token id="t3">الشارع</token>
      <token id="t4">فيه</token>
      <token id="t5">حركةة</token>
      <token id="t6">على</token>
      <token id="t7">غير</token>
      <token id="t8">العادة</token>
    </annotated_arabizi>
    <auto_transliteration>لا انا عندي الشارع fyh حركة على غير العادة</auto_transliteration>
    <corrected_transliteration>لا انا عندي الشارع fyh حركة على غير العادة</corrected_transliteration>
    <retokenized_transliteration>لا انا عندي الشارع fyh حركة على غير العادة</retokenized_transliteration>
    <messages>
      <message id="m0030" time="2013-08-30 07:10:00 UTC" participant="139230">لا انا عندي الشارع فيه حركةة على غير العادة</message>
    </messages>
  </su>
  <su id="s17">
    <source>بيقولوا حنفضل نمشي 1 لحد 15 سبتمبر</source>
    <annotated_arabizi>
      <token id="t0">بيقولوا</token>
      <token id="t1">حنفضل</token>
      <token id="t2">نمشي</token>
      <token id="t3">1</token>
      <token id="t4">لحد</token>
      <token id="t5" tag="foreign">15</token>
      <token id="t6">سبتمبر</token>
    </annotated_arabizi>
    <auto_transliteration>بيقولوا حنفضل نمشي 1 لحد 15 سبتمبر</auto_transliteration>
    <corrected_transliteration>بيقولوا حنفضل نمشي 1 لحد 15 سبتمبر</corrected_transliteration>
    <retokenized_transliteration>بيقولوا حنفضل نمشي 1 لحد 15 سبتمبر</retokenized_transliteration>
    <messages>
      <message id="m0031" time="2013-08-30 07:10:00 UTC" participant="139880">بيقولوا حنفضل نمشي 1 لحد 15 سبتمبر</message>
    </messages>
  </su>
  <su id="s18">
    <source>وكمان النور اتقطع من الساعة 6 والله كويس انا اصﻻ كنت اجازة الاسبوع دا عشان كنت بافرش الشقة</source>
    <annotated_arabizi>
      <token id="t0">وكمان</token>
      <token id="t1">النور</token>
      <token id="t2">اتقطع</token>
      <token id="t3">من</token>
      <token id="t4">الساعة</token>
      <token id="t5">6</token>
      <token id="t6">والله</token>
      <token id="t7">كويس</token>
      <token id="t8">انا</token>
      <token id="t9">اصلا</token>
      <token id="t10">كنت</token>
      <token id="t11">اجازة</token>
      <token id="t12">الاسبوع</token>
      <token id="t13">دا</token>
      <token id="t14">عشان</token>
      <token id="t15">كنت</token>
      <token id="t16">بافرش</token>
      <token id="t17">الشقة</token>
    </annotated_arabizi>
    <auto_transliteration>وكمان النور اتقطع mn الساعة 6 والله كويس انا أصلا كنت AjAzp الاسبوع dA عشأن كنت بافرش الشقة</auto_transliteration>
    <corrected_transliteration>وكمان النور اتقطع mn الساعة 6 والله كويس انا أصلا كنت AjAzp الاسبوع dA عشأن كنت بافرش الشقة</corrected_transliteration>
    <retokenized_transliteration>وكمان النور اتقطع mn الساعة 6 والله كويس انا أصلا كنت AjAzp الاسبوع dA عشأن كنت بافرش الشقة</retokenized_transliteration>
    <messages>
      <message id="m0032" time="2013-08-30 07:10:00 UTC" participant="139230">وكمان النور اتقطع من الساعة 6</message>
      <message id="m0033" time="2013-08-30 07:10:00 UTC" participant="139230">والله كويس</message>
      <message id="m0034" time="2013-08-30 07:11:00 UTC" participant="139230">انا اصﻻ كنت اجازة الاسبوع دا عشان كنت بافرش الشقة</message>
    </messages>
  </su>
  <su id="s19">
    <source>خلصتي الحمدلله انا كمان كنت اجازة</source>
    <annotated_arabizi>
      <token id="t0">خلصتي</token>
      <token id="t1">الحمدلله</token>
      <token id="t2">انا</token>
      <token id="t3">كمان</token>
      <token id="t4">كنت</token>
      <token id="t5">اجازة</token>
    </annotated_arabizi>
    <auto_transliteration>خلصتي الحمدلاله انا كمان كنت AjAzp</auto_transliteration>
    <corrected_transliteration>خلصتي الحمدلاله انا كمان كنت AjAzp</corrected_transliteration>
    <retokenized_transliteration>خلصتي الحمدلاله انا كمان كنت AjAzp</retokenized_transliteration>
    <messages>
      <message id="m0035" time="2013-08-30 07:12:00 UTC" participant="139880">انا كمان كنت اجازة</message>
      <message id="m0036" time="2013-08-30 07:12:00 UTC" participant="139880">خلصتي الحمدلله</message>
    </messages>
  </su>
  <su id="s20">
    <source>ايوا لسه مخلصة</source>
    <annotated_arabizi>
      <token id="t0">ايوا</token>
      <token id="t1">لسه</token>
      <token id="t2">مخلصة</token>
    </annotated_arabizi>
    <auto_transliteration>ايوا لسه مخلصة</auto_transliteration>
    <corrected_transliteration>ايوا لسه مخلصة</corrected_transliteration>
    <retokenized_transliteration>ايوا لسه مخلصة</retokenized_transliteration>
    <messages>
      <message id="m0037" time="2013-08-30 07:13:00 UTC" participant="139230">ايوا لسه مخلصة</message>
    </messages>
  </su>
  <su id="s21">
    <source>الحمدلله</source>
    <annotated_arabizi>
      <token id="t0">الحمدلله</token>
    </annotated_arabizi>
    <auto_transliteration>الحمدلاله</auto_transliteration>
    <corrected_transliteration>الحمدلاله</corrected_transliteration>
    <retokenized_transliteration>الحمدلاله</retokenized_transliteration>
    <messages>
      <message id="m0038" time="2013-08-30 07:13:00 UTC" participant="139880">الحمدلله</message>
    </messages>
  </su>
  <su id="s22">
    <source>في شوية حاجات بسيطة تتعمل بس خلاص مش قادرة</source>
    <annotated_arabizi>
      <token id="t0">في</token>
      <token id="t1">شوية</token>
      <token id="t2">حاجات</token>
      <token id="t3">بسيطة</token>
      <token id="t4">تتعمل</token>
      <token id="t5">بس</token>
      <token id="t6">خلاص</token>
      <token id="t7">مش</token>
      <token id="t8">قادرة</token>
    </annotated_arabizi>
    <auto_transliteration>fy شوية HAjAt بسيطة تتعمل bs خلاص مش قادرة</auto_transliteration>
    <corrected_transliteration>fy شوية HAjAt بسيطة تتعمل bs خلاص مش قادرة</corrected_transliteration>
    <retokenized_transliteration>fy شوية HAjAt بسيطة تتعمل bs خلاص مش قادرة</retokenized_transliteration>
    <messages>
      <message id="m0039" time="2013-08-30 07:14:00 UTC" participant="139230">في شوية حاجات بسيطة تتعمل بس خلاص مش قادرة</message>
    </messages>
  </su>
  <su id="s23">
    <source>الحمد لله</source>
    <annotated_arabizi>
      <token id="t0">الحمد</token>
      <token id="t1">لله</token>
    </annotated_arabizi>
    <auto_transliteration>الحمد llh</auto_transliteration>
    <corrected_transliteration>الحمد llh</corrected_transliteration>
    <retokenized_transliteration>الحمد llh</retokenized_transliteration>
    <messages>
      <message id="m0040" time="2013-08-30 07:14:00 UTC" participant="139230">الحمد لله</message>
    </messages>
  </su>
</conversation>
