<?xml version="1.0" encoding="UTF-8"?>
<conversation id="CHT_ARZ_20121118.0000" medium="IM" donated="true">
  <su id="s0">
    <messages>
      <message id="m0000" medium="IM" time="2012-11-18 21:12:03 UTC" participant="138112">Enty 3arfa en f trip bokra hah</message>
    </messages>
    <body type="original">Enty 3arfa en f trip bokra hah</body><body type="transliterated">انتي عارفه ان ف تراب بكره هه</body>
  </su>
  <su id="s1">
    <messages>
      <message id="m0001" medium="IM" time="2012-11-18 21:12:15 UTC" participant="138311">Ahh seme3t :D</message>
    </messages>
    <body type="original">Ahh seme3t :D</body><body type="transliterated">اه سمعت : يد</body>
  </su>
  <su id="s2">
    <messages>
      <message id="m0002" medium="IM" time="2012-11-18 21:12:45 UTC" participant="138112">Hatro7i?</message>
      <message id="m0003" medium="IM" time="2012-11-18 21:12:52 UTC" participant="138112">El trip feeha attendance</message>
    </messages>
    <body type="original">Hatro7i? El trip feeha attendance</body><body type="transliterated">هتروحي ? هل تراب فيها attendance</body>
  </su>
  <su id="s3">
    <messages>
      <message id="m0004" medium="IM" time="2012-11-18 21:12:55 UTC" participant="138311">Ahh</message>
      <message id="m0005" medium="IM" time="2012-11-18 21:12:58 UTC" participant="138311">Isa</message>
      <message id="m0006" medium="IM" time="2012-11-18 21:13:03 UTC" participant="138311">:D</message>
      <message id="m0007" medium="IM" time="2012-11-18 21:13:07 UTC" participant="138311">Ah mna 3arfa</message>
    </messages>
    <body type="original">Ahh Isa :D Ah mna 3arfa</body><body type="transliterated">اه اسه : اد اه منا عارفه</body>
  </su>
  <su id="s4">
    <messages>
      <message id="m0008" medium="IM" time="2012-11-18 21:13:23 UTC" participant="138112">W bel uniform kaman 3la fekra</message>
    </messages>
    <body type="original">W bel uniform kaman 3la fekra</body><body type="transliterated">و بل uniform كمان علي فكره</body>
  </su>
  <su id="s5">
    <messages>
      <message id="m0009" medium="IM" time="2012-11-18 21:14:46 UTC" participant="138311">W malloo :D</message>
    </messages>
    <body type="original">W malloo :D</body><body type="transliterated">و ماله : يد</body>
  </su>
  <su id="s6">
    <messages>
      <message id="m0010" medium="IM" time="2012-11-18 21:15:36 UTC" participant="138112">Bas Ana halbes jeans badal el pantalon w hastahbel:D</message>
    </messages>
    <body type="original">Bas Ana halbes jeans badal el pantalon w hastahbel:D</body><body type="transliterated">بس انا هلبس قانص بدل ال بنطلون و hastahbel : يد</body>
  </su>
  <su id="s7">
    <messages>
      <message id="m0011" medium="IM" time="2012-11-18 21:15:56 UTC" participant="138311">Hahahaha</message>
      <message id="m0012" medium="IM" time="2012-11-18 21:16:02 UTC" participant="138311">Eshta</message>
    </messages>
    <body type="original">Hahahaha Eshta</body><body type="transliterated">hahahaha اشدة</body>
  </su>
  <su id="s8">
    <messages>
      <message id="m0013" medium="IM" time="2012-11-18 21:25:37 UTC" participant="138112">Enty kaman hha</message>
    </messages>
    <body type="original">Enty kaman hha</body><body type="transliterated">انتي كمان هه</body>
  </su>
  <su id="s9">
    <messages>
      <message id="m0014" medium="IM" time="2012-11-18 21:25:57 UTC" participant="138112">Enty 3arfa eni rawa7t men el trip 1:20 belel</message>
    </messages>
    <body type="original">Enty 3arfa eni rawa7t men el trip 1:20 belel</body><body type="transliterated">انتي عارفه اني روحت من ال تراب 1 : 20 بليل</body>
  </su>
  <su id="s10">
    <messages>
      <message id="m0015" medium="IM" time="2012-11-18 21:26:14 UTC" participant="138311">O_O</message>
    </messages>
    <body type="original">O_O</body><body type="transliterated">و ـ و</body>
  </su>
  <su id="s11">
    <messages>
      <message id="m0016" medium="IM" time="2012-11-18 21:26:20 UTC" participant="138311">Omg Whyyyy</message>
      <message id="m0017" medium="IM" time="2012-11-18 21:26:30 UTC" participant="138311">Enti sakna gamb el skool</message>
    </messages>
    <body type="original">Omg Whyyyy Enti sakna gamb el skool</body><body type="transliterated">عمق وهي انت ساكنه جنب ال skool</body>
  </su>
  <su id="s12">
    <messages>
      <message id="m0018" medium="IM" time="2012-11-18 21:26:38 UTC" participant="138112">Ahhh</message>
    </messages>
    <body type="original">Ahhh</body><body type="transliterated">اه</body>
  </su>
  <su id="s13">
    <messages>
      <message id="m0019" medium="IM" time="2012-11-18 21:26:46 UTC" participant="138311">Rowa7oki met2a5er?</message>
    </messages>
    <body type="original">Rowa7oki met2a5er?</body><body type="transliterated">rowa7oki متاخر ?</body>
  </su>
  <su id="s14">
    <messages>
      <message id="m0020" medium="IM" time="2012-11-18 21:26:53 UTC" participant="138112">E7na aslan et7arakna 11 men el sa7ara</message>
    </messages>
    <body type="original">E7na aslan et7arakna 11 men el sa7ara</body><body type="transliterated">احنا اصلا اتحركنا 11 من ال سحره</body>
  </su>
  <su id="s15">
    <messages>
      <message id="m0021" medium="IM" time="2012-11-18 21:27:09 UTC" participant="138311">Ya allaah</message>
      <message id="m0022" medium="IM" time="2012-11-18 21:27:12 UTC" participant="138311">Leh kda</message>
    </messages>
    <body type="original">Ya allaah Leh kda</body><body type="transliterated">يا الله ليه كده</body>
  </su>
  <su id="s16">
    <messages>
      <message id="m0023" medium="IM" time="2012-11-18 21:27:39 UTC" participant="138112">Mashakel kteera b2a</message>
      <message id="m0024" medium="IM" time="2012-11-18 21:27:40 UTC" participant="138112">Hh</message>
    </messages>
    <body type="original">Mashakel kteera b2a Hh</body><body type="transliterated">مشاكل كتيره بقى هه</body>
  </su>
  <su id="s17">
    <messages>
      <message id="m0025" medium="IM" time="2012-11-18 21:27:43 UTC" participant="138112">*haha</message>
    </messages>
    <body type="original">*haha</body><body type="transliterated">ذ هه</body>
  </su>
  <su id="s18">
    <messages>
      <message id="m0026" medium="IM" time="2012-11-18 21:28:01 UTC" participant="138112">E7na a3adna fel sa7ara fel dalma men 7:30 le 11</message>
      <message id="m0027" medium="IM" time="2012-11-18 21:28:08 UTC" participant="138112">Ta5ayali</message>
    </messages>
    <body type="original">E7na a3adna fel sa7ara fel dalma men 7:30 le 11 Ta5ayali</body><body type="transliterated">احنا قعدنا فل سحره فل ضلمه من 7 : 30 لي 11 تخيلي</body>
  </su>
  <su id="s19">
    <messages>
      <message id="m0028" medium="IM" time="2012-11-18 21:31:33 UTC" participant="138311">Yalhwii</message>
    </messages>
    <body type="original">Yalhwii</body><body type="transliterated">يالهوي</body>
  </su>
  <su id="s20">
    <messages>
      <message id="m0029" medium="IM" time="2012-11-18 21:31:49 UTC" participant="138311">Ana 2omi kanet hat2tlni low 23adt kol da xD</message>
    </messages>
    <body type="original">Ana 2omi kanet hat2tlni low 23adt kol da xD</body><body type="transliterated">انا امي كانت هتقتلني لو قعدت كل ده xd</body>
  </su>
  <su id="s21">
    <messages>
      <message id="m0030" medium="IM" time="2012-11-18 21:37:05 UTC" participant="138112">Bas begad makansh f 2id 7ad</message>
    </messages>
    <body type="original">Bas begad makansh f 2id 7ad</body><body type="transliterated">بس بجد مكنش ف ايد حد</body>
  </su>
  <su id="s22">
    <messages>
      <message id="m0031" medium="IM" time="2012-11-18 21:50:23 UTC" participant="138311">Mmm</message>
      <message id="m0032" medium="IM" time="2012-11-18 21:50:33 UTC" participant="138311">Bs rege3to met2a5ar awi</message>
    </messages>
    <body type="original">Mmm Bs rege3to met2a5ar awi</body><body type="transliterated">مم بس رجعت متاخر اوي</body>
  </su>
  <su id="s23">
    <messages>
      <message id="m0033" medium="IM" time="2012-11-18 21:59:20 UTC" participant="138112">Awyyyy Ana aslan nemt fel tari2 w kolo kan msh taye2 nafso</message>
      <message id="m0034" medium="IM" time="2012-11-18 21:59:34 UTC" participant="138112">W el weather kan bard awy</message>
      <message id="m0035" medium="IM" time="2012-11-18 21:59:42 UTC" participant="138112">Ana 3eyet aslan</message>
    </messages>
    <body type="original">Awyyyy Ana aslan nemt fel tari2 w kolo kan msh taye2 nafso W el weather kan bard awy Ana 3eyet aslan</body><body type="transliterated">اوي انا اصلا نمت فل طريق و كله كان مش طايق نفسه و ال ويثير كان برد اوي انا عيط اصلا</body>
  </su>
  <su id="s24">
    <messages>
      <message id="m0036" medium="IM" time="2012-11-18 22:16:31 UTC" participant="138311">Salamteeek :(</message>
    </messages>
    <body type="original">Salamteeek :(</body><body type="transliterated">سلامتك : (</body>
  </su>
  <su id="s25">
    <messages>
      <message id="m0037" medium="IM" time="2012-11-18 22:16:39 UTC" participant="138311">Ahh 3andoko 7aa2</message>
    </messages>
    <body type="original">Ahh 3andoko 7aa2</body><body type="transliterated">اه عندكم حق</body>
  </su>
</conversation>
